pylinuxauto/__init__.py
pylinuxauto/__version__.py
pylinuxauto/assertx.py
pylinuxauto/config.py
pylinuxauto/exceptions.py
pylinuxauto/file.py
pylinuxauto/plugin.py
pylinuxauto/screenshot.py
pylinuxauto/sleepx.py
pylinuxauto/utils.py
pylinuxauto/attr/__init__.py
pylinuxauto/attr/depends.py
pylinuxauto/attr/dogtail/__init__.py
pylinuxauto/attr/dogtail/config.py
pylinuxauto/attr/dogtail/distro.py
pylinuxauto/attr/dogtail/dump.py
pylinuxauto/attr/dogtail/errors.py
pylinuxauto/attr/dogtail/i18n.py
pylinuxauto/attr/dogtail/logging.py
pylinuxauto/attr/dogtail/path.py
pylinuxauto/attr/dogtail/predicate.py
pylinuxauto/attr/dogtail/procedural.py
pylinuxauto/attr/dogtail/rawinput.py
pylinuxauto/attr/dogtail/sessions.py
pylinuxauto/attr/dogtail/tc.py
pylinuxauto/attr/dogtail/tree.py
pylinuxauto/attr/dogtail/utils.py
pylinuxauto/attr/dogtail/version.py
pylinuxauto/attr/dogtail/wrapped.py
pylinuxauto/attr/icons/dogtail-head-48.png
pylinuxauto/attr/icons/dogtail-head.svg
pylinuxauto/attr/icons/dogtail-tail-48.png
pylinuxauto/attr/icons/dogtail-tail.svg
pylinuxauto/attr/sniff/sniff.desktop
pylinuxauto/attr/sniff/sniff.py
pylinuxauto/attr/sniff/sniff.ui
pylinuxauto/attr/sniff/icons/button.xpm
pylinuxauto/attr/sniff/icons/checkbutton.xpm
pylinuxauto/attr/sniff/icons/checkmenuitem.xpm
pylinuxauto/attr/sniff/icons/colorselection.xpm
pylinuxauto/attr/sniff/icons/combo.xpm
pylinuxauto/attr/sniff/icons/dialog.xpm
pylinuxauto/attr/sniff/icons/image.xpm
pylinuxauto/attr/sniff/icons/label.xpm
pylinuxauto/attr/sniff/icons/menubar.xpm
pylinuxauto/attr/sniff/icons/menuitem.xpm
pylinuxauto/attr/sniff/icons/notebook.xpm
pylinuxauto/attr/sniff/icons/scrolledwindow.xpm
pylinuxauto/attr/sniff/icons/spinbutton.xpm
pylinuxauto/attr/sniff/icons/statusbar.xpm
pylinuxauto/attr/sniff/icons/table.xpm
pylinuxauto/attr/sniff/icons/text.xpm
pylinuxauto/attr/sniff/icons/toolbar.xpm
pylinuxauto/attr/sniff/icons/tree.xpm
pylinuxauto/attr/sniff/icons/treeitem.xpm
pylinuxauto/attr/sniff/icons/unknown.xpm
pylinuxauto-2024.12.25.dist-info/METADATA
pylinuxauto-2024.12.25.dist-info/WHEEL
pylinuxauto-2024.12.25.dist-info/entry_points.txt
pylinuxauto-2024.12.25.dist-info/licenses/LICENSE
pylinuxauto-2024.12.25.dist-info/RECORD
