Metadata-Version: 2.1
Name: pylinuxauto
Version: 2024.12.25
Author-email: mikigo <huangmingqiang@uniontech.com>
License: GPL2.0
License-File: LICENSE
Requires-Python: >=3.6
Requires-Dist: funnylog2
Requires-Dist: nocmd
Requires-Dist: python3-xlib; platform_system == 'Linux' and python_version >= '3.0'
Provides-Extra: all
Requires-Dist: opencv-python; extra == 'all'
Requires-Dist: paddleocr; extra == 'all'
Requires-Dist: paddlepaddle; extra == 'all'
